mypy/__init__.py
mypy/__main__.py
mypy/api.py
mypy/applytype.py
mypy/argmap.py
mypy/binder.py
mypy/bogus_type.py
mypy/build.py
mypy/cache.py
mypy/checker.py
mypy/checker_shared.py
mypy/checker_state.py
mypy/checkexpr.py
mypy/checkmember.py
mypy/checkpattern.py
mypy/checkstrformat.py
mypy/config_parser.py
mypy/constant_fold.py
mypy/constraints.py
mypy/copytype.py
mypy/defaults.py
mypy/dmypy_os.py
mypy/dmypy_server.py
mypy/dmypy_util.py
mypy/erasetype.py
mypy/error_formatter.py
mypy/errorcodes.py
mypy/errors.py
mypy/evalexpr.py
mypy/expandtype.py
mypy/exprtotype.py
mypy/fastparse.py
mypy/find_sources.py
mypy/fixup.py
mypy/freetree.py
mypy/fscache.py
mypy/fswatcher.py
mypy/gclogger.py
mypy/git.py
mypy/graph_utils.py
mypy/indirection.py
mypy/infer.py
mypy/inspections.py
mypy/ipc.py
mypy/join.py
mypy/literals.py
mypy/lookup.py
mypy/main.py
mypy/maptype.py
mypy/meet.py
mypy/memprofile.py
mypy/message_registry.py
mypy/messages.py
mypy/metastore.py
mypy/mixedtraverser.py
mypy/modulefinder.py
mypy/moduleinspect.py
mypy/mro.py
mypy/nodes.py
mypy/operators.py
mypy/options.py
mypy/parse.py
mypy/partially_defined.py
mypy/patterns.py
mypy/plugin.py
mypy/py.typed
mypy/pyinfo.py
mypy/reachability.py
mypy/refinfo.py
mypy/renaming.py
mypy/report.py
mypy/scope.py
mypy/semanal.py
mypy/semanal_classprop.py
mypy/semanal_enum.py
mypy/semanal_infer.py
mypy/semanal_main.py
mypy/semanal_namedtuple.py
mypy/semanal_newtype.py
mypy/semanal_pass1.py
mypy/semanal_shared.py
mypy/semanal_typeargs.py
mypy/semanal_typeddict.py
mypy/sharedparse.py
mypy/solve.py
mypy/split_namespace.py
mypy/state.py
mypy/stats.py
mypy/strconv.py
mypy/stubdoc.py
mypy/stubgen.py
mypy/stubgenc.py
mypy/stubinfo.py
mypy/stubtest.py
mypy/stubutil.py
mypy/subtypes.py
mypy/suggestions.py
mypy/traverser.py
mypy/treetransform.py
mypy/tvar_scope.py
mypy/type_visitor.py
mypy/typeanal.py
mypy/typeops.py
mypy/types.py
mypy/types_utils.py
mypy/typestate.py
mypy/typetraverser.py
mypy/typevars.py
mypy/typevartuples.py
mypy/util.py
mypy-1.18.1.dist-info/licenses/LICENSE
mypy-1.18.1.dist-info/METADATA
mypy-1.18.1.dist-info/WHEEL
mypy-1.18.1.dist-info/entry_points.txt
mypy-1.18.1.dist-info/top_level.txt
mypy-1.18.1.dist-info/RECORD
